raptureAPI/__init__.py
raptureAPI/multipart.py
raptureAPI/raptureAPI.py
raptureAPI-3.0.42.dist-info/DESCRIPTION.rst
raptureAPI-3.0.42.dist-info/METADATA
raptureAPI-3.0.42.dist-info/RECORD
raptureAPI-3.0.42.dist-info/WHEEL
raptureAPI-3.0.42.dist-info/metadata.json
raptureAPI-3.0.42.dist-info/top_level.txt
