Metadata-Version: 2.0
Name: raptureAPI
Version: 3.0.42
Summary: raptureAPI: Incapture Technologies LLC
Home-page: http://incapturetechnologies.com/
Author: Incapture Technologies LLC
Author-email: info@incapturetechnologies.com
License: Incapture Technologies LLC
Platform: UNKNOWN
